encipher.py
encipher-0.1.0.dist-info/LICENSE
encipher-0.1.0.dist-info/WHEEL
encipher-0.1.0.dist-info/METADATA
encipher-0.1.0.dist-info/RECORD
