Metadata-Version: 2.1
Name: encipher
Version: 0.1.0
Summary: Randomly encrypts text
License: MIT
Author: Brandon
Author-email: brandonskerritt51@gmail.com
Requires-Python: >=3.8,<4.0
Classifier: License :: OSI Approved :: MIT License
Classifier: Programming Language :: Python :: 3
Classifier: Programming Language :: Python :: 3.8
